LICENSE
MANIFEST.in
README.md
setup.py
wscutils/__init__.py
wscutils/__version__.py
wscutils/argparse_helper.py
wscutils/log_factory.py
wscutils/method_timer.py
wscutils/redis_queue.py
wscutils/redis_throttled_queue.py
wscutils/settings_wrapper.py
wscutils/stats_collector.py
wscutils/zookeeper_watcher.py
wscutils.egg-info/PKG-INFO
wscutils.egg-info/SOURCES.txt
wscutils.egg-info/dependency_links.txt
wscutils.egg-info/requires.txt
wscutils.egg-info/top_level.txt